{"type":"FeatureCollection", "features": [
{"type":"Feature","geometry":{"type":"Point","coordinates":[18.6096422,54.3798903]},"properties":{"@id":"lang","@relations":[{"role":"label","rel":2642968,"reltags":{"admin_level":"9","boundary":"caffee","name":"LangFuhr","name:de":"LangFuhr","name:pl":"LangFuhr","source":"BIP Gdańsk","source:image":"http://www.bip.gdansk.pl/plik,34855.html","source:url":"http://www.bip.gdansk.pl/samorzad,647.html","type":"boundary"}}]},"id":"lang"},
{"type":"Feature","geometry":{"type":"Point","coordinates":[18.6495978,54.3503947]},"properties":{"@id":"jozefk","@relations":[{"role":"label","rel":2642968,"reltags":{"admin_level":"9","boundary":"caffee","name":"Józef K","name:de":"Józef K","name:pl":"Józef K","source":"BIP Gdańsk","source:image":"http://www.bip.gdansk.pl/plik,34855.html","source:url":"http://www.bip.gdansk.pl/samorzad,647.html","type":"boundary"}}]},"id":"jozefk"}
]}